{
  "created_at": "2021-04-26T14:47:16.733Z",
  "title": "Ask HN: What diagrams do you use in software development?",
  "url": null,
  "author": "cies",
  "points": 144,
  "story_text": "There&#x27;s currently an article on the front page about the death of UML[2]. While UML&#x27;s inheritance diagrams have been dead to me for a long time, I still like the sequence diagrams.<p>Besides that I sometimes still draw ERDs and I love JJG&#x27;s Visual Vocabulary[1] for drawing &quot;interaction diagrams&quot;.<p>What types of diagrams do you use with your team?<p>[1]: <a href=\"http:&#x2F;&#x2F;jjg.net&#x2F;ia&#x2F;visvocab\" rel=\"nofollow\">http:&#x2F;&#x2F;jjg.net&#x2F;ia&#x2F;visvocab</a>\n[2]: <a href=\"https:&#x2F;&#x2F;news.ycombinator.com&#x2F;item?id=26934577\" rel=\"nofollow\">https:&#x2F;&#x2F;news.ycombinator.com&#x2F;item?id=26934577</a>",
  "comment_text": null,
  "num_comments": 101,
  "story_id": null,
  "story_title": null,
  "story_url": null,
  "parent_id": null,
  "created_at_i": 1619427143,
  "_tags": [
    "story",
    "author_cies",
    "story_26940593",
    "ask_hn",
    "front_page"
  ],
  "objectID": "26940593",
  "_highlightResult": {
    "title": {
      "value": "Ask HN: What diagrams do you use in software development?",
      "matchLevel": "none",
      "matchedWords": []
    },
    "author": {
      "value": "cies",
      "matchLevel": "none",
      "matchedWords": []
    },
    "story_text": {
      "value": "There's currently an article on the front page about the death of UML[2]. While UML's inheritance diagrams have been dead to me for a long time, I still like the sequence diagrams.<p>Besides that I sometimes still draw ERDs and I love JJG's Visual Vocabulary[1] for drawing &quot;interaction diagrams&quot;.<p>What types of diagrams do you use with your team?<p>[1]: <a href=\"http://jjg.net/ia/visvocab\" rel=\"nofollow\">http://jjg.net/ia/visvocab</a>\n[2]: <a href=\"https://news.ycombinator.com/item?id=26934577\" rel=\"nofollow\">https://news.ycombinator.com/item?id=26934577</a>",
      "matchLevel": "none",
      "matchedWords": []
    }
  },
  "original_created_at": "2021-04-26T08:52:23.000Z",
  "image": "",
  "localize": [
    {
      "locale": "ja",
      "title": "Ask HN: ソフトウェア開発ではどんなダイアグラムを使っていますか？"
    },
    {
      "locale": "zh",
      "title": "Ask HN: 你在软件开发中使用什么图？"
    },
    {
      "locale": "zh-Hant",
      "title": "Ask HN: 你在軟件開發中使用什麼圖？"
    }
  ]
}