{
  "created_at": "2021-02-24T10:14:29.088Z",
  "title": "LinkedIn is building a gig marketplace",
  "url": "https://aimgroup.com/2021/02/22/linkedin-building-gig-marketplace/",
  "author": "ArtTimeInvestor",
  "points": 385,
  "story_text": null,
  "comment_text": null,
  "num_comments": 118,
  "story_id": null,
  "story_title": null,
  "story_url": null,
  "parent_id": null,
  "created_at_i": 1614148859,
  "_tags": [
    "story",
    "author_ArtTimeInvestor",
    "story_26247278",
    "front_page"
  ],
  "objectID": "26247278",
  "_highlightResult": {
    "title": {
      "value": "LinkedIn is building a gig marketplace",
      "matchLevel": "none",
      "matchedWords": []
    },
    "url": {
      "value": "https://aimgroup.com/2021/02/22/linkedin-building-gig-marketplace/",
      "matchLevel": "none",
      "matchedWords": []
    },
    "author": {
      "value": "ArtTimeInvestor",
      "matchLevel": "none",
      "matchedWords": []
    }
  },
  "original_created_at": "2021-02-24T06:40:59.000Z",
  "image": "https://aimgroup.com/wp-content/uploads/2021/02/1612767907416.jpg",
  "localize": [
    {
      "locale": "zh",
      "title": "LinkedIn正在建立一个gig市场"
    },
    {
      "locale": "zh-Hant",
      "title": "LinkedIn正在建立一個gig市場"
    }
  ],
  "source_updated_at": 1614332904966
}