{
  "created_at": "Thu Aug 19 14:58:21 +0000 2021",
  "id_str": "1428366224870625280",
  "full_text": "Breaking: U.S. Capitol Police ordered an evacuation of a House of Representatives office building near the Library of Congress after a suspicious vehicle was found in the area https://t.co/qtqelNCwLJ",
  "display_text_range": [
    0,
    199
  ],
  "entities": {
    "hashtags": [],
    "symbols": [],
    "user_mentions": [],
    "urls": [
      {
        "url": "https://t.co/qtqelNCwLJ",
        "expanded_url": "https://on.wsj.com/37X8CAW",
        "display_url": "on.wsj.com/37X8CAW",
        "indices": [
          176,
          199
        ]
      }
    ]
  },
  "user": {
    "name": "The Wall Street Journal",
    "screen_name": "WSJ",
    "profile_image_url_https": "https://pbs.twimg.com/profile_images/971415515754266624/zCX0q9d5_normal.jpg"
  },
  "retweet_count": 50,
  "favorite_count": 113,
  "possibly_sensitive": false,
  "original_created_at": "Thu Aug 19 14:40:20 +0000 2021"
}