{
  "created_at": "Wed Aug 25 14:43:30 +0000 2021",
  "id_str": "1430534196842336257",
  "full_text": "From @WSJopinion: The Taliban says get out by Aug. 31. The U.S. President agrees. Biden is bowing to Taliban demands, writes The Editorial Board. https://t.co/rktQXmmaUZ",
  "display_text_range": [
    0,
    169
  ],
  "entities": {
    "hashtags": [],
    "symbols": [],
    "user_mentions": [
      {
        "screen_name": "WSJopinion",
        "name": "WSJ Editorial Page",
        "id": 7228682,
        "id_str": "7228682",
        "indices": [
          5,
          16
        ]
      }
    ],
    "urls": [
      {
        "url": "https://t.co/rktQXmmaUZ",
        "expanded_url": "https://on.wsj.com/3BemfYS",
        "display_url": "on.wsj.com/3BemfYS",
        "indices": [
          146,
          169
        ]
      }
    ]
  },
  "user": {
    "name": "The Wall Street Journal",
    "screen_name": "WSJ",
    "profile_image_url_https": "https://pbs.twimg.com/profile_images/971415515754266624/zCX0q9d5_normal.jpg"
  },
  "retweet_count": 35,
  "favorite_count": 102,
  "possibly_sensitive": false,
  "original_created_at": "Wed Aug 25 14:15:05 +0000 2021"
}