{
  "author": "MidnightLostChild_",
  "original_created_utc": 1627057719,
  "title": "Gents of Reddit, how do you hint your partner that you want to have s*x with her without being too obvious?",
  "created_utc": 1627068247,
  "selftext_html": "<!-- SC_OFF --><div class=\"md\"><p>Like seriously.. It&#39;s hard for us first-timers you know</p>\n</div><!-- SC_ON -->",
  "score": 110,
  "permalink": "/r/TooAfraidToAsk/comments/oq5zrq/gents_of_reddit_how_do_you_hint_your_partner_that/",
  "subreddit": "TooAfraidToAsk",
  "id": "oq5zrq",
  "is_self": true,
  "media": null,
  "is_video": false,
  "the_new_excerpt": "Like seriously.. It's hard for us first-timers you know"
}