{
  "videoId": "Fklvhaj7drg",
  "channelId": "UCu59H8LNti6mwvcGRMge5PA",
  "title": "Natti Natasha x Farina x Cazzu x La Duraca - Las Nenas [Official Video]",
  "link": "https://www.youtube.com/watch?v=Fklvhaj7drg",
  "pubDate": "2021-03-04T23:00:14.000Z",
  "author": "Natti Natasha",
  "id": "yt:video:Fklvhaj7drg",
  "isoDate": "2021-03-04T23:00:14.000Z",
  "description": "Natti Natasha x Farina x Cazzu x La Duraca - Las Nenas [Official Video] \r\nSuscríbete:  https://youtube.com/c/NattiNatasha\r\n\r\n🎵 Música: \r\nStream: https://smarturl.it/LasNenasSingle\r\n\r\nLetra: \r\n\r\n\r\nCoro\r\n\r\nDonde están las nenas que quieren sateo sateo sateo sateo \r\ny aunque andamos fina hoy quiero un perreo perreo perreo perreo \r\nNalga pa’aqui, nalga pa’alla y tra tra ta tra \r\nNalga pa’aqui, nalga pa’alla, tra tra ta tra tra tra \r\n\r\nDesorden, desorden no quiero que se me comporten \r\nDesorden, desorden si van a hacer algo, la misión aborden \r\n\r\n\r\nFarina: \r\nPerreo supremo \r\nNivel de tu culo? extremo \r\nMoney aquí tenemos y lo que no existe \r\nLo hacemos \r\nEsta Jefa fina dice presente \r\nSi es pal despeluque de frente \r\nReunión de culos loquera calculo detrás de estas nalgas todos estos papichulos \r\nDe botellas traje un container \r\nYa están aquí para todas mis partners \r\nUn perri vestido oliendo a designer \r\nMis piernas brillando como mi Black Diners. \r\n\r\n\r\nCazzu: \r\nHey, esta noche me voy Pa la calle \r\nA ti no te doy tanto detalle \r\nPero mis nenas saben la hora, el lugar, no me fallen \r\nY... no andamos buscando un suggar daddy, si estamos piloteando un bugatti y cada vez \r\nque yo llego al party, tu sabe’ \r\nLo muevo to the left \r\nLo muevo to the right \r\nNo me gustó tu taste \r\nPapi no eres mi size \r\n\r\n\r\nCoro : \r\nDonde están las nenas que quieren sateo sateo sateo sateo \r\ny aunque andamos fina hoy quiero un perreo perreo perreo perreo \r\nNalga pa’aqui, nalga pa’alla y tra tra ta tra \r\nNalga pa’aqui, nalga pa’alla, y tra tra ta tra tra tra \r\n\r\nDesorden, desorden no quiero que se me comporten \r\nDesorden, desorden si van a hacer algo, la misión aborden \r\n\r\nLa Duraca: \r\nYo quiero un perreo que me haga perder el cache \r\nQuitarme las tacas dorche la botella de vino Cheval descorche \r\nDespués de 3 más quien guía la porche \r\nSon más de las 12 y empieza el perreo afincau \r\nTú jevo Ta medio picau \r\nYo que estoy soltera, no respeto hombres casau \r\nY esta noche él sería el indicau \r\nQue puede pasar que rompamos rompamos \r\nHasta que salga el sol no nos vamos \r\nLevanten las copas por las envidiosas brindamos \r\nno llegan acá donde estamos \r\n\r\n\r\nNatti Natasha: \r\nSalimos fresh, muy cute \r\nMira el diseño de mi pedicure \r\nque lo combino con el manicure \r\nTamo’ puesta pal revolu \r\nNo me heches la culpa \r\nculpa al grey goose uuuu \r\nLa boobie rebotan rebotan \r\nAndamo mamota jevota \r\nSomos la banda subiendo la nota \r\nHazme una 69, no me salga chota (cero chotas) \r\nSúbete al paddle y va’ a choca’ con la versión femenina del father \r\nCreamos la ola juntitas o sola \r\nTodas somos una \r\nLes pregunto ahora! \r\n\r\n\r\nCoro :\r\n\r\nDonde estan las nenas que quieren sateo sateo sateo sateo \r\ny aunque andamos fina hoy quiero un perreo perreo perreo perreo \r\nNalga pa’aqui, nalga pa’alla y tra tra ta tra \r\nNalga pa’aqui, nalga pa’alla, y tra tra ta tra tra tra \r\n\r\nDesorden, desorden no quiero que se me comporten \r\nDesorden, desorden si van a hacer algo, la misión aborden \r\n\r\n\r\nRedes: \r\n \r\nNatti Natasha:\r\nFacebook: https://www.facebook.com/NattiNatashaOfficial\r\nTwitter: https://twitter.com/NattiNatasha\r\nInstagram: https://www.instagram.com/nattinatasha/\r\n\r\n\r\nPlaylists by Natti Natasha: \r\n➤ilumiNATTI : http://primo.vi/ABCUY4\r\n➤Official Videos: https://bit.ly/2E3soOh\r\n➤Lo Mejor: http://primo.vi/BfQrSu\r\n➤Natti Natasha Live: http://primo.vi/MSCfda\r\n\r\n\r\nEscucha el playlist oficial de Pina Records: La Formula: https://spoti.fi/3mXV3av\r\n\r\nBooking/Contrataciones\r\n(787) 743-1100 / booking@pinarecords.net \r\nPress & Media: press@pinarecords.net\r\n\r\nOfficial Music Video by Natti Natasha x Farina x Cazzu x La Duraca \"Las Nenas\" (C) 2021 Pina Records\r\n\r\n#NattiNatasha #LasNenas",
  "thumbnail": {
    "url": "https://i3.ytimg.com/vi/Fklvhaj7drg/hqdefault.jpg",
    "width": "480",
    "height": "360"
  },
  "starRating": {
    "count": "171283",
    "average": "4.92",
    "min": "1",
    "max": "5"
  },
  "statistics": {
    "views": "1202471"
  },
  "original_created_at": "2021-03-04T23:00:14.000Z",
  "created_at": "2021-03-05T18:28:22.493Z",
  "tags": [
    "NattiNatasha",
    "LasNenas"
  ]
}