{
  "author": "rediver87",
  "original_created_utc": 1633397101,
  "title": "Debt free thanks to BTC",
  "created_utc": 1633408237,
  "selftext_html": "<!-- SC_OFF --><div class=\"md\"><p>I’m pumped. 7 years of debt disappearing in less than 1 year thanks to the wonderful BTC. And the best part is I only need to cash out 15ish% of my bag. Stoked!</p>\n\n<p>Edit - admittedly it’s not huge debt but it’s debt that’s been following me around for years that I was unable to clear due to being in an out of work with health problems. Thankfully life has been much more stable the past 1.5 years which in turn allowed me to invest in BTC!</p>\n</div><!-- SC_ON -->",
  "score": 178,
  "permalink": "/r/Bitcoin/comments/q1ka73/debt_free_thanks_to_btc/",
  "subreddit": "Bitcoin",
  "id": "q1ka73",
  "is_self": true,
  "media": null,
  "is_video": false,
  "the_new_excerpt": "I’m pumped. 7 years of debt disappearing in less than 1 year thanks to the\nwonderful BTC. And the best part is I only need to cash out 15ish% of my bag.\nStoked!\n\nEdit - admittedly it’s not huge debt but it’s debt that’s been following me\naround for years that I was unable to clear due to being in an…"
}