{
  "approved_at_utc": null,
  "subreddit": "pics",
  "selftext": "",
  "author_fullname": "t2_3z3xvjt5",
  "saved": false,
  "mod_reason_title": null,
  "gilded": 0,
  "clicked": false,
  "title": "Step dad providing for our family during trying times in Texas",
  "link_flair_richtext": [],
  "subreddit_name_prefixed": "r/pics",
  "hidden": false,
  "pwls": 6,
  "link_flair_css_class": null,
  "downs": 0,
  "thumbnail_height": 140,
  "top_awarded_type": "ACTIVE",
  "hide_score": false,
  "name": "t3_lmcmtd",
  "quarantine": false,
  "link_flair_text_color": "dark",
  "upvote_ratio": 0.85,
  "author_flair_background_color": null,
  "subreddit_type": "public",
  "ups": 109539,
  "total_awards_received": 544,
  "media_embed": {},
  "thumbnail_width": 140,
  "author_flair_template_id": null,
  "is_original_content": false,
  "user_reports": [],
  "secure_media": null,
  "is_reddit_media_domain": true,
  "is_meta": false,
  "category": null,
  "secure_media_embed": {},
  "link_flair_text": null,
  "can_mod_post": false,
  "score": 109539,
  "approved_by": null,
  "author_premium": true,
  "thumbnail": "https://b.thumbs.redditmedia.com/YCOOIFsJjejFQOqUbArOmm6CSSuKwljN9F9YGxN0Yis.jpg",
  "edited": false,
  "author_flair_css_class": null,
  "author_flair_richtext": [],
  "gildings": {
    "gid_1": 106
  },
  "post_hint": "image",
  "content_categories": [
    "photography"
  ],
  "is_self": false,
  "mod_note": null,
  "created": 1613647844,
  "link_flair_type": "text",
  "wls": 6,
  "removed_by_category": null,
  "banned_by": null,
  "author_flair_type": "text",
  "domain": "i.redd.it",
  "allow_live_comments": true,
  "selftext_html": null,
  "likes": null,
  "suggested_sort": null,
  "banned_at_utc": null,
  "url_overridden_by_dest": "https://i.redd.it/hfx4irvco5i61.jpg",
  "view_count": null,
  "archived": false,
  "no_follow": false,
  "is_crosspostable": false,
  "pinned": false,
  "over_18": false,
  "preview": {
    "images": [
      {
        "source": {
          "url": "https://preview.redd.it/hfx4irvco5i61.jpg?auto=webp&s=f27688770ac60045be47d6593febe8ee596af054",
          "width": 750,
          "height": 940
        },
        "resolutions": [
          {
            "url": "https://preview.redd.it/hfx4irvco5i61.jpg?width=108&crop=smart&auto=webp&s=e71101a986e485a3cd8dde74379ef48e9852012d",
            "width": 108,
            "height": 135
          },
          {
            "url": "https://preview.redd.it/hfx4irvco5i61.jpg?width=216&crop=smart&auto=webp&s=60bc7c47ec9cb41ea558aec95e60ef5cf2abbbe1",
            "width": 216,
            "height": 270
          },
          {
            "url": "https://preview.redd.it/hfx4irvco5i61.jpg?width=320&crop=smart&auto=webp&s=405e5bb25180af97c46e15e66d5e8335d386b827",
            "width": 320,
            "height": 401
          },
          {
            "url": "https://preview.redd.it/hfx4irvco5i61.jpg?width=640&crop=smart&auto=webp&s=f9290c9d6e8d2031cb118544f7601b0ab2bbba1f",
            "width": 640,
            "height": 802
          }
        ],
        "variants": {},
        "id": "C0FBOyWomyIDJynpGktjdJxtR8nGTFZmW4nwJhfDGb4"
      }
    ],
    "enabled": true
  },
  "awarders": [],
  "media_only": false,
  "can_gild": false,
  "spoiler": false,
  "locked": false,
  "author_flair_text": null,
  "treatment_tags": [],
  "visited": false,
  "removed_by": null,
  "num_reports": null,
  "distinguished": null,
  "subreddit_id": "t5_2qh0u",
  "mod_reason_by": null,
  "removal_reason": null,
  "link_flair_background_color": "",
  "id": "lmcmtd",
  "is_robot_indexable": true,
  "report_reasons": null,
  "author": "Kodai-in-a-ditch",
  "discussion_type": null,
  "num_comments": 3818,
  "send_replies": true,
  "whitelist_status": "all_ads",
  "contest_mode": false,
  "mod_reports": [],
  "author_patreon_flair": false,
  "author_flair_text_color": null,
  "permalink": "/r/pics/comments/lmcmtd/step_dad_providing_for_our_family_during_trying/",
  "parent_whitelist_status": "all_ads",
  "stickied": false,
  "url": "https://i.redd.it/hfx4irvco5i61.jpg",
  "subreddit_subscribers": 26806492,
  "created_utc": 1613651137,
  "num_crossposts": 10,
  "media": null,
  "is_video": false,
  "original_created_utc": 1613619044,
  "the_new_excerpt": "",
  "localize": [
    {
      "locale": "zh",
      "title": "继父在德州的艰难时期为我们的家庭提供了保障。"
    },
    {
      "locale": "zh-Hant",
      "title": "繼父在德州的艱難時期爲我們的家庭提供了保障。"
    }
  ],
  "source_updated_at": 1614332869135
}