{
  "author": "_Zev",
  "original_created_utc": 1635907574,
  "title": "If before I die, I swallow the human limit of popcorn kernels and they unknowingly cremate me. Will those pop from inside my body?",
  "created_utc": 1635938704,
  "selftext_html": null,
  "score": 113,
  "permalink": "/r/NoStupidQuestions/comments/qlkzku/if_before_i_die_i_swallow_the_human_limit_of/",
  "subreddit": "NoStupidQuestions",
  "id": "qlkzku",
  "is_self": true,
  "media": null,
  "is_video": false,
  "the_new_excerpt": ""
}