{
  "approved_at_utc": null,
  "subreddit": "Unexpected",
  "selftext": "",
  "author_fullname": "t2_nftqw",
  "saved": false,
  "mod_reason_title": null,
  "gilded": 1,
  "clicked": false,
  "title": "Stone skipping.",
  "link_flair_richtext": [],
  "subreddit_name_prefixed": "r/Unexpected",
  "hidden": false,
  "pwls": 6,
  "link_flair_css_class": null,
  "downs": 0,
  "thumbnail_height": 66,
  "top_awarded_type": "ACTIVE",
  "hide_score": false,
  "name": "t3_kprcgs",
  "quarantine": false,
  "link_flair_text_color": "dark",
  "upvote_ratio": 0.87,
  "author_flair_background_color": null,
  "subreddit_type": "public",
  "ups": 81552,
  "total_awards_received": 163,
  "media_embed": {
    "content": "<iframe class=\"embedly-embed\" src=\"https://cdn.embedly.com/widgets/media.html?src=https%3A%2F%2Fgfycat.com%2Fifr%2Fscaredalivecuckoo&display_name=Gfycat&url=https%3A%2F%2Fgfycat.com%2Fscaredalivecuckoo&image=https%3A%2F%2Fthumbs.gfycat.com%2FScaredAliveCuckoo-size_restricted.gif&key=2aa3c4d5f3de4f5b9120b660ad850dc9&type=text%2Fhtml&schema=gfycat\" width=\"460\" height=\"218\" scrolling=\"no\" title=\"Gfycat embed\" frameborder=\"0\" allow=\"autoplay; fullscreen\" allowfullscreen=\"true\"></iframe>",
    "width": 460,
    "scrolling": false,
    "height": 218
  },
  "thumbnail_width": 140,
  "author_flair_template_id": null,
  "is_original_content": false,
  "user_reports": [],
  "secure_media": {
    "type": "gfycat.com",
    "oembed": {
      "provider_url": "https://gfycat.com",
      "description": "Watch and share Stone Skipping. GIFs by esberat on Gfycat",
      "title": "Stone Skipping.",
      "type": "video",
      "author_name": "Gfycat",
      "height": 218,
      "width": 460,
      "html": "<iframe class=\"embedly-embed\" src=\"https://cdn.embedly.com/widgets/media.html?src=https%3A%2F%2Fgfycat.com%2Fifr%2Fscaredalivecuckoo&display_name=Gfycat&url=https%3A%2F%2Fgfycat.com%2Fscaredalivecuckoo&image=https%3A%2F%2Fthumbs.gfycat.com%2FScaredAliveCuckoo-size_restricted.gif&key=2aa3c4d5f3de4f5b9120b660ad850dc9&type=text%2Fhtml&schema=gfycat\" width=\"460\" height=\"218\" scrolling=\"no\" title=\"Gfycat embed\" frameborder=\"0\" allow=\"autoplay; fullscreen\" allowfullscreen=\"true\"></iframe>",
      "thumbnail_width": 527,
      "version": "1.0",
      "provider_name": "Gfycat",
      "thumbnail_url": "https://thumbs.gfycat.com/ScaredAliveCuckoo-size_restricted.gif",
      "thumbnail_height": 250
    }
  },
  "is_reddit_media_domain": false,
  "is_meta": false,
  "category": null,
  "secure_media_embed": {
    "content": "<iframe class=\"embedly-embed\" src=\"https://cdn.embedly.com/widgets/media.html?src=https%3A%2F%2Fgfycat.com%2Fifr%2Fscaredalivecuckoo&display_name=Gfycat&url=https%3A%2F%2Fgfycat.com%2Fscaredalivecuckoo&image=https%3A%2F%2Fthumbs.gfycat.com%2FScaredAliveCuckoo-size_restricted.gif&key=2aa3c4d5f3de4f5b9120b660ad850dc9&type=text%2Fhtml&schema=gfycat\" width=\"460\" height=\"218\" scrolling=\"no\" title=\"Gfycat embed\" frameborder=\"0\" allow=\"autoplay; fullscreen\" allowfullscreen=\"true\"></iframe>",
    "width": 460,
    "scrolling": false,
    "media_domain_url": "https://www.redditmedia.com/mediaembed/kprcgs",
    "height": 218
  },
  "link_flair_text": null,
  "can_mod_post": false,
  "score": 81552,
  "approved_by": null,
  "author_premium": true,
  "thumbnail": "https://b.thumbs.redditmedia.com/EQPILnGJQ4YcVQbb7O4Mx5g6Vw47GBkP2yF4s7m2BvY.jpg",
  "edited": false,
  "author_flair_css_class": null,
  "author_flair_richtext": [],
  "gildings": {
    "gid_1": 38,
    "gid_2": 1
  },
  "post_hint": "rich:video",
  "content_categories": null,
  "is_self": false,
  "mod_note": null,
  "created": 1609731700,
  "link_flair_type": "text",
  "wls": 6,
  "removed_by_category": null,
  "banned_by": null,
  "author_flair_type": "text",
  "domain": "gfycat.com",
  "allow_live_comments": true,
  "selftext_html": null,
  "likes": null,
  "suggested_sort": "confidence",
  "banned_at_utc": null,
  "url_overridden_by_dest": "https://gfycat.com/scaredalivecuckoo",
  "view_count": null,
  "archived": false,
  "no_follow": false,
  "is_crosspostable": false,
  "pinned": false,
  "over_18": false,
  "preview": {
    "images": [
      {
        "source": {
          "url": "https://external-preview.redd.it/NyEw-oDZXujEal9Q_vMqeN_fpxI_Z0_5nGKwpAj7eq4.jpg?auto=webp&s=8357c9e0c5abfc17aeb28bd30ae0005c752151f1",
          "width": 527,
          "height": 250
        },
        "resolutions": [
          {
            "url": "https://external-preview.redd.it/NyEw-oDZXujEal9Q_vMqeN_fpxI_Z0_5nGKwpAj7eq4.jpg?width=108&crop=smart&auto=webp&s=fb258cbad89b1f35d0e23ac3c4fb6f12bad06293",
            "width": 108,
            "height": 51
          },
          {
            "url": "https://external-preview.redd.it/NyEw-oDZXujEal9Q_vMqeN_fpxI_Z0_5nGKwpAj7eq4.jpg?width=216&crop=smart&auto=webp&s=d5ad12bf510b05f57cd50acf0564957a059fa5bb",
            "width": 216,
            "height": 102
          },
          {
            "url": "https://external-preview.redd.it/NyEw-oDZXujEal9Q_vMqeN_fpxI_Z0_5nGKwpAj7eq4.jpg?width=320&crop=smart&auto=webp&s=7c5168338b00dbfd1ec6b893d2500361e9a99081",
            "width": 320,
            "height": 151
          }
        ],
        "variants": {},
        "id": "kkjuAgXdr9FT18KN7rDr-BHGPKC4Or72XDwnbXWtmT8"
      }
    ],
    "reddit_video_preview": {
      "bitrate_kbps": 600,
      "fallback_url": "https://v.redd.it/fl8hr4zn76961/DASH_240.mp4",
      "height": 201,
      "width": 426,
      "scrubber_media_url": "https://v.redd.it/fl8hr4zn76961/DASH_96.mp4",
      "dash_url": "https://v.redd.it/fl8hr4zn76961/DASHPlaylist.mpd",
      "duration": 7,
      "hls_url": "https://v.redd.it/fl8hr4zn76961/HLSPlaylist.m3u8",
      "is_gif": true,
      "transcoding_status": "completed"
    },
    "enabled": false
  },
  "awarders": [],
  "media_only": false,
  "can_gild": false,
  "spoiler": false,
  "locked": false,
  "author_flair_text": null,
  "treatment_tags": [],
  "visited": false,
  "removed_by": null,
  "num_reports": null,
  "distinguished": null,
  "subreddit_id": "t5_2w67q",
  "mod_reason_by": null,
  "removal_reason": null,
  "link_flair_background_color": "",
  "id": "kprcgs",
  "is_robot_indexable": true,
  "report_reasons": null,
  "author": "esberat",
  "discussion_type": null,
  "num_comments": 458,
  "send_replies": true,
  "whitelist_status": "all_ads",
  "contest_mode": false,
  "mod_reports": [],
  "author_patreon_flair": false,
  "author_flair_text_color": null,
  "permalink": "/r/Unexpected/comments/kprcgs/stone_skipping/",
  "parent_whitelist_status": "all_ads",
  "stickied": false,
  "url": "https://gfycat.com/scaredalivecuckoo",
  "subreddit_subscribers": 3468559,
  "created_utc": 1609744327,
  "num_crossposts": 34,
  "media": {
    "type": "gfycat.com",
    "oembed": {
      "provider_url": "https://gfycat.com",
      "description": "Watch and share Stone Skipping. GIFs by esberat on Gfycat",
      "title": "Stone Skipping.",
      "type": "video",
      "author_name": "Gfycat",
      "height": 218,
      "width": 460,
      "html": "<iframe class=\"embedly-embed\" src=\"https://cdn.embedly.com/widgets/media.html?src=https%3A%2F%2Fgfycat.com%2Fifr%2Fscaredalivecuckoo&display_name=Gfycat&url=https%3A%2F%2Fgfycat.com%2Fscaredalivecuckoo&image=https%3A%2F%2Fthumbs.gfycat.com%2FScaredAliveCuckoo-size_restricted.gif&key=2aa3c4d5f3de4f5b9120b660ad850dc9&type=text%2Fhtml&schema=gfycat\" width=\"460\" height=\"218\" scrolling=\"no\" title=\"Gfycat embed\" frameborder=\"0\" allow=\"autoplay; fullscreen\" allowfullscreen=\"true\"></iframe>",
      "thumbnail_width": 527,
      "version": "1.0",
      "provider_name": "Gfycat",
      "thumbnail_url": "https://thumbs.gfycat.com/ScaredAliveCuckoo-size_restricted.gif",
      "thumbnail_height": 250
    }
  },
  "is_video": false,
  "original_created_utc": 1609702900,
  "the_new_excerpt": "",
  "localize": [
    {
      "locale": "zh",
      "title": "跳石。"
    },
    {
      "locale": "zh-Hant",
      "title": "跳石。"
    }
  ],
  "source_updated_at": 1610100727960
}