{
  "videoId": "xHotXbGZiFY",
  "channelId": "UC81hVmI5eEBIt3s3HQpJd_w",
  "title": "White Woman's Instagram -- Bo Burnham (from \"Inside\" -- ALBUM OUT NOW)",
  "link": "https://www.youtube.com/watch?v=xHotXbGZiFY",
  "pubDate": "2021-06-10T14:00:34.000Z",
  "author": "boburnham",
  "id": "yt:video:xHotXbGZiFY",
  "isoDate": "2021-06-10T14:00:34.000Z",
  "description": "listen to album here: https://boburnham.lnk.to/INSIDE\n\ninside now streaming on netflix. hope you enjoy.",
  "thumbnail": {
    "url": "https://i1.ytimg.com/vi/xHotXbGZiFY/hqdefault.jpg",
    "width": "480",
    "height": "360"
  },
  "starRating": {
    "count": "178093",
    "average": "4.94",
    "min": "1",
    "max": "5"
  },
  "statistics": {
    "views": "3365724"
  },
  "original_created_at": "2021-06-10T14:00:34.000Z",
  "created_at": "2021-06-10T21:23:37.665Z",
  "tags": [],
  "localize": [
    {
      "locale": "ja",
      "description": "アルバムの試聴はこちら： https://boburnham.lnk.to/INSIDE\n\nInsideはNetflixで配信中です。",
      "title": "White Woman's Instagram -- Bo Burnham (from \"Inside\" -- ALBUM OUT NOW)"
    },
    {
      "locale": "zh",
      "description": "在此收听专辑：https://boburnham.lnk.to/INSIDE\n\n里面的内容现在在Netflix上流传，希望你喜欢。",
      "title": "白人女子的Instagram - Bo Burnham (来自 \"Inside\" - ALBUM OUT NOW)"
    },
    {
      "locale": "zh-Hant",
      "description": "在此收聽專輯：https://boburnham.lnk.to/INSIDE\n\n裏面的內容現在在Netflix上流傳，希望你喜歡。",
      "title": "白人女子的Instagram - Bo Burnham (來自 \"Inside\" - ALBUM OUT NOW)"
    }
  ],
  "source_updated_at": 1624009752257
}