{
  "approved_at_utc": null,
  "subreddit": "todayilearned",
  "selftext": "",
  "author_fullname": "t2_600muuy8",
  "saved": false,
  "mod_reason_title": null,
  "gilded": 0,
  "clicked": false,
  "title": "TIL about the April Fool’s Day prank in 1980 by the BBC who reported that Big Ben was going to change to a digital clock. Some people were so shocked by the announcement that they phoned in to complain.",
  "link_flair_richtext": [],
  "subreddit_name_prefixed": "r/todayilearned",
  "hidden": false,
  "pwls": 6,
  "link_flair_css_class": null,
  "downs": 0,
  "thumbnail_height": 93,
  "top_awarded_type": null,
  "hide_score": false,
  "name": "t3_nyv4af",
  "quarantine": false,
  "link_flair_text_color": "dark",
  "upvote_ratio": 0.9,
  "author_flair_background_color": null,
  "subreddit_type": "public",
  "ups": 75021,
  "total_awards_received": 15,
  "media_embed": {},
  "thumbnail_width": 140,
  "author_flair_template_id": null,
  "is_original_content": false,
  "user_reports": [],
  "secure_media": null,
  "is_reddit_media_domain": false,
  "is_meta": false,
  "category": null,
  "secure_media_embed": {},
  "link_flair_text": null,
  "can_mod_post": false,
  "score": 75021,
  "approved_by": null,
  "is_created_from_ads_ui": false,
  "author_premium": true,
  "thumbnail": "https://b.thumbs.redditmedia.com/E2u9VJhzZfSA5TlYQ2cOOR3ro9NSUQV1Bb38de45GJg.jpg",
  "edited": false,
  "author_flair_css_class": null,
  "author_flair_richtext": [],
  "gildings": {
    "gid_1": 3
  },
  "post_hint": "link",
  "content_categories": null,
  "is_self": false,
  "mod_note": null,
  "created": 1623615624,
  "link_flair_type": "text",
  "wls": 6,
  "removed_by_category": null,
  "banned_by": null,
  "author_flair_type": "text",
  "domain": "bbc.co.uk",
  "allow_live_comments": true,
  "selftext_html": null,
  "likes": null,
  "suggested_sort": null,
  "banned_at_utc": null,
  "url_overridden_by_dest": "https://www.bbc.co.uk/bitesize/articles/z7gbxyc",
  "view_count": null,
  "archived": false,
  "no_follow": false,
  "is_crosspostable": false,
  "pinned": false,
  "over_18": false,
  "preview": {
    "images": [
      {
        "source": {
          "url": "https://external-preview.redd.it/KJoMzNB-1XmY1CnSpTT1eM52M0jAePhOeJiQ31hSAao.jpg?auto=webp&s=9882efa7901ce83489ae26f92e2c0ac46a73ec97",
          "width": 1200,
          "height": 800
        },
        "resolutions": [
          {
            "url": "https://external-preview.redd.it/KJoMzNB-1XmY1CnSpTT1eM52M0jAePhOeJiQ31hSAao.jpg?width=108&crop=smart&auto=webp&s=bb19d2cc17b980ef88d760ec5ccc5f4d3d535674",
            "width": 108,
            "height": 72
          },
          {
            "url": "https://external-preview.redd.it/KJoMzNB-1XmY1CnSpTT1eM52M0jAePhOeJiQ31hSAao.jpg?width=216&crop=smart&auto=webp&s=8bc8240086459c51eb3ed623f4fa8fd4f6b206f6",
            "width": 216,
            "height": 144
          },
          {
            "url": "https://external-preview.redd.it/KJoMzNB-1XmY1CnSpTT1eM52M0jAePhOeJiQ31hSAao.jpg?width=320&crop=smart&auto=webp&s=0386447226b4aef348f3b4019545a5ec7d703f03",
            "width": 320,
            "height": 213
          },
          {
            "url": "https://external-preview.redd.it/KJoMzNB-1XmY1CnSpTT1eM52M0jAePhOeJiQ31hSAao.jpg?width=640&crop=smart&auto=webp&s=e8531cd8cbd19fc5dd918d628a607598ac9bdeb5",
            "width": 640,
            "height": 426
          },
          {
            "url": "https://external-preview.redd.it/KJoMzNB-1XmY1CnSpTT1eM52M0jAePhOeJiQ31hSAao.jpg?width=960&crop=smart&auto=webp&s=40f42eec8f4c9520fff56b44db7ba64c99faf69d",
            "width": 960,
            "height": 640
          },
          {
            "url": "https://external-preview.redd.it/KJoMzNB-1XmY1CnSpTT1eM52M0jAePhOeJiQ31hSAao.jpg?width=1080&crop=smart&auto=webp&s=9e17e15e089f49296bc051e62831a0491e6c2d00",
            "width": 1080,
            "height": 720
          }
        ],
        "variants": {},
        "id": "6XzCtWtMTrpqTmx9xiap730rvkb2NapBitfZsIpDqDI"
      }
    ],
    "enabled": false
  },
  "awarders": [],
  "media_only": false,
  "can_gild": false,
  "spoiler": false,
  "locked": false,
  "author_flair_text": null,
  "treatment_tags": [],
  "visited": false,
  "removed_by": null,
  "num_reports": null,
  "distinguished": null,
  "subreddit_id": "t5_2qqjc",
  "mod_reason_by": null,
  "removal_reason": null,
  "link_flair_background_color": "",
  "id": "nyv4af",
  "is_robot_indexable": true,
  "report_reasons": null,
  "author": "thebelsnickle1991",
  "discussion_type": null,
  "num_comments": 1002,
  "send_replies": false,
  "whitelist_status": "all_ads",
  "contest_mode": false,
  "mod_reports": [],
  "author_patreon_flair": false,
  "author_flair_text_color": null,
  "permalink": "/r/todayilearned/comments/nyv4af/til_about_the_april_fools_day_prank_in_1980_by/",
  "parent_whitelist_status": "all_ads",
  "stickied": false,
  "url": "https://www.bbc.co.uk/bitesize/articles/z7gbxyc",
  "subreddit_subscribers": 25614830,
  "created_utc": 1623670403,
  "num_crossposts": 2,
  "media": null,
  "is_video": false,
  "original_created_utc": 1623586824,
  "the_new_excerpt": ""
}