{
  "author": "No_Permanent_Address",
  "original_created_utc": 1635156556,
  "title": "Why would you NOT go back in time to live in 1980s America?",
  "created_utc": 1635175271,
  "selftext_html": "<!-- SC_OFF --><div class=\"md\"><p>There is a large portion of the internet that romanticizes the 80s. What about those that don’t?</p>\n</div><!-- SC_ON -->",
  "score": 110,
  "permalink": "/r/NoStupidQuestions/comments/qfdgol/why_would_you_not_go_back_in_time_to_live_in/",
  "subreddit": "NoStupidQuestions",
  "id": "qfdgol",
  "is_self": true,
  "media": null,
  "is_video": false,
  "the_new_excerpt": "There is a large portion of the internet that romanticizes the 80s. What about\nthose that don’t?"
}