{
  "videoId": "R4R14vEC-g0",
  "channelId": "UC_PQ7gGEKIwJv0YsnxH3dUw",
  "title": "Mo3 - Last Time (Official Video)",
  "link": "https://www.youtube.com/watch?v=R4R14vEC-g0",
  "pubDate": "2021-11-11T18:01:34.000Z",
  "author": "HSM",
  "id": "yt:video:R4R14vEC-g0",
  "isoDate": "2021-11-11T18:01:34.000Z",
  "description": "Listen to the album \"Shottaz 4Eva (Deluxe)\". Out now!\nStream: https://music.empi.re/shottaz4evadeluxe.oyd\n\n#Mo3 #Shottaz4Eva #HSM\n\nOfficial Video by Mo3 - Last Time© 2021 H$M Music / EMPIRE",
  "thumbnail": {
    "url": "https://i3.ytimg.com/vi/R4R14vEC-g0/hqdefault.jpg",
    "width": "480",
    "height": "360"
  },
  "starRating": {
    "count": "11700",
    "average": "4.98",
    "min": "1",
    "max": "5"
  },
  "statistics": {
    "views": "87813"
  },
  "original_created_at": "2021-11-11T18:01:34.000Z",
  "created_at": "2021-11-12T01:14:30.208Z",
  "tags": [
    "Mo3",
    "Shottaz4Eva",
    "HSM"
  ]
}