{
  "created_at": "Fri Sep 17 12:55:51 +0000 2021",
  "id_str": "1438842619631751168",
  "full_text": "RT @PedderSophie: Macron's covid passports have been controversial, risky--and a spectacular success. By September 15 74% of the French (an…",
  "display_text_range": [
    0,
    140
  ],
  "entities": {
    "hashtags": [],
    "symbols": [],
    "user_mentions": [
      {
        "screen_name": "PedderSophie",
        "name": "Sophie Pedder",
        "id": 558889051,
        "id_str": "558889051",
        "indices": [
          3,
          16
        ]
      }
    ],
    "urls": []
  },
  "user": {
    "name": "The Economist",
    "screen_name": "TheEconomist",
    "profile_image_url_https": "https://pbs.twimg.com/profile_images/879361767914262528/HdRauDM-_normal.jpg"
  },
  "retweet_count": 104,
  "favorite_count": 0,
  "original_created_at": "Fri Sep 17 12:29:47 +0000 2021",
  "retweeted_status": {
    "created_at": "Fri Sep 17 09:32:37 +0000 2021",
    "id_str": "1438798031881744385",
    "full_text": "Macron's covid passports have been controversial, risky--and a spectacular success. By September 15 74% of the French (and 88% of over 12s) had received at least one dose, up from 54% on July 12. This is now higher than in 🇺🇸, 🇬🇧and 🇩🇪 in @TheEconomist\nhttps://t.co/zPxtHysMWg",
    "display_text_range": [
      0,
      276
    ],
    "entities": {
      "hashtags": [],
      "symbols": [],
      "user_mentions": [
        {
          "screen_name": "TheEconomist",
          "name": "The Economist",
          "id": 5988062,
          "id_str": "5988062",
          "indices": [
            239,
            252
          ]
        }
      ],
      "urls": [
        {
          "url": "https://t.co/zPxtHysMWg",
          "expanded_url": "https://www.economist.com/europe/2021/09/18/how-france-tackled-vaccine-hesitancy",
          "display_url": "economist.com/europe/2021/09…",
          "indices": [
            253,
            276
          ]
        }
      ]
    },
    "user": {
      "name": "Sophie Pedder",
      "screen_name": "PedderSophie",
      "profile_image_url_https": "https://pbs.twimg.com/profile_images/988719485334024192/LIHHSmQJ_normal.jpg"
    },
    "retweet_count": 104,
    "favorite_count": 275,
    "possibly_sensitive": false
  }
}