{
  "created_at": "2021-01-10T17:12:10.172Z",
  "title": "Skynet – Build a Free Internet",
  "url": "https://siasky.net/",
  "author": "thesausageking",
  "points": 259,
  "story_text": null,
  "comment_text": null,
  "num_comments": 112,
  "story_id": null,
  "story_title": null,
  "story_url": null,
  "parent_id": null,
  "created_at_i": 1610253591,
  "_tags": [
    "story",
    "author_thesausageking",
    "story_25710151",
    "front_page"
  ],
  "objectID": "25710151",
  "_highlightResult": {
    "title": {
      "value": "Skynet – Build a Free Internet",
      "matchLevel": "none",
      "matchedWords": []
    },
    "url": {
      "value": "https://siasky.net/",
      "matchLevel": "none",
      "matchedWords": []
    },
    "author": {
      "value": "thesausageking",
      "matchLevel": "none",
      "matchedWords": []
    }
  },
  "original_created_at": "2021-01-10T04:39:51.000Z",
  "image": "https://siasky.net/icons/icon-512x512.png",
  "localize": [
    {
      "locale": "zh",
      "title": "天网-打造免费互联网"
    },
    {
      "locale": "zh-Hant",
      "title": "天網-打造免費互聯網"
    }
  ],
  "source_updated_at": 1610706390714
}