{
  "author": "davidbauer",
  "original_created_utc": 1640792135,
  "title": "African flags people can correctly indentify [OC]",
  "created_utc": 1640798758,
  "selftext_html": null,
  "score": 201,
  "preview": {
    "images": [
      {
        "source": {
          "url": "https://preview.redd.it/ohsy4d5a2i881.png?auto=webp&amp;s=9c86ca675ddd35fe22f0a887f65a7e3e1622e511",
          "width": 2466,
          "height": 2980
        },
        "resolutions": [
          {
            "url": "https://preview.redd.it/ohsy4d5a2i881.png?width=108&amp;crop=smart&amp;auto=webp&amp;s=b2f37d474eab7f8501dcfabc94998e9275fa1f95",
            "width": 108,
            "height": 130
          },
          {
            "url": "https://preview.redd.it/ohsy4d5a2i881.png?width=216&amp;crop=smart&amp;auto=webp&amp;s=65148e701efebf29f0876dd5f36e466360b5b1bb",
            "width": 216,
            "height": 261
          },
          {
            "url": "https://preview.redd.it/ohsy4d5a2i881.png?width=320&amp;crop=smart&amp;auto=webp&amp;s=6afa0b43274d786722216770962fb8be95e410b1",
            "width": 320,
            "height": 386
          },
          {
            "url": "https://preview.redd.it/ohsy4d5a2i881.png?width=640&amp;crop=smart&amp;auto=webp&amp;s=9a647178be6ed82ef1c124e0975b4f2cc87198b2",
            "width": 640,
            "height": 773
          },
          {
            "url": "https://preview.redd.it/ohsy4d5a2i881.png?width=960&amp;crop=smart&amp;auto=webp&amp;s=cd3f2785abf76489a6331073eab1f6315ed27456",
            "width": 960,
            "height": 1160
          },
          {
            "url": "https://preview.redd.it/ohsy4d5a2i881.png?width=1080&amp;crop=smart&amp;auto=webp&amp;s=57c3008a0f7fc33008ced5d4559ad34a2cea6234",
            "width": 1080,
            "height": 1305
          }
        ],
        "variants": {},
        "id": "abk3DpjP3IRIp6kKpb00qBeNjyI0SBOCE3CxS7bvjCk"
      }
    ],
    "enabled": true
  },
  "permalink": "/r/dataisbeautiful/comments/rrav28/african_flags_people_can_correctly_indentify_oc/",
  "subreddit": "dataisbeautiful",
  "id": "rrav28",
  "is_self": false,
  "media": null,
  "is_video": false,
  "the_new_excerpt": "",
  "localize": [
    {
      "locale": "ja",
      "title": "アフリカの国旗を正しく認識できる人【OC"
    },
    {
      "locale": "zh",
      "title": "非洲的旗帜人们可以正确地识别[OC]"
    },
    {
      "locale": "zh-Hant",
      "title": "非洲的旗幟人們可以正確地識別[OC]"
    }
  ]
}